ansys/aedt/core/__init__.py
ansys/aedt/core/aedt_logger.py
ansys/aedt/core/base.py
ansys/aedt/core/circuit.py
ansys/aedt/core/circuit_netlist.py
ansys/aedt/core/common_rpc.py
ansys/aedt/core/desktop.py
ansys/aedt/core/edb.py
ansys/aedt/core/emit.py
ansys/aedt/core/filtersolutions.py
ansys/aedt/core/help.py
ansys/aedt/core/hfss.py
ansys/aedt/core/hfss3dlayout.py
ansys/aedt/core/icepak.py
ansys/aedt/core/maxwell.py
ansys/aedt/core/maxwellcircuit.py
ansys/aedt/core/mechanical.py
ansys/aedt/core/mixins.py
ansys/aedt/core/q3d.py
ansys/aedt/core/rmxprt.py
ansys/aedt/core/twinbuilder.py
ansys/aedt/core/application/__init__.py
ansys/aedt/core/application/aedt_file_management.py
ansys/aedt/core/application/aedt_objects.py
ansys/aedt/core/application/aedt_units.py
ansys/aedt/core/application/analysis.py
ansys/aedt/core/application/analysis_3d.py
ansys/aedt/core/application/analysis_3d_layout.py
ansys/aedt/core/application/analysis_circuit_netlist.py
ansys/aedt/core/application/analysis_hf.py
ansys/aedt/core/application/analysis_icepak.py
ansys/aedt/core/application/analysis_maxwell_circuit.py
ansys/aedt/core/application/analysis_nexxim.py
ansys/aedt/core/application/analysis_r_m_xprt.py
ansys/aedt/core/application/analysis_twin_builder.py
ansys/aedt/core/application/design.py
ansys/aedt/core/application/design_solutions.py
ansys/aedt/core/application/job_manager.py
ansys/aedt/core/application/variables.py
ansys/aedt/core/cli/__init__.py
ansys/aedt/core/cli/common.py
ansys/aedt/core/cli/config.py
ansys/aedt/core/cli/doc.py
ansys/aedt/core/cli/panels.py
ansys/aedt/core/cli/process.py
ansys/aedt/core/emit_core/__init__.py
ansys/aedt/core/emit_core/couplings.py
ansys/aedt/core/emit_core/emit_constants.py
ansys/aedt/core/emit_core/emit_function_validator.py
ansys/aedt/core/emit_core/emit_schematic.py
ansys/aedt/core/emit_core/nodes/emit_node.py
ansys/aedt/core/emit_core/nodes/emitter_node.py
ansys/aedt/core/emit_core/nodes/generated/__init__.py
pyaedt-0.24.0.dist-info/licenses/LICENSE
pyaedt-0.24.0.dist-info/METADATA
pyaedt-0.24.0.dist-info/WHEEL
pyaedt-0.24.0.dist-info/entry_points.txt
pyaedt-0.24.0.dist-info/top_level.txt
pyaedt-0.24.0.dist-info/RECORD
