Metadata-Version: 2.4
Name: pyaedt
Version: 0.24.0
Summary: High-level Python API for Ansys Electronics Desktop Framework
Author-email: "ANSYS, Inc." <pyansys.core@ansys.com>
Maintainer-email: "ANSYS, Inc." <pyansys.core@ansys.com>
License-Expression: MIT
Project-URL: Bugs, https://github.com/ansys/pyaedt/issues
Project-URL: Documentation, https://aedt.docs.pyansys.com
Project-URL: Source, https://github.com/ansys/pyaedt
Project-URL: Discussions, https://github.com/ansys/pyaedt/discussions
Project-URL: Releases, https://github.com/ansys/pyaedt/releases
Project-URL: Changelog, https://github.com/ansys/pyaedt/blob/main/doc/source/changelog.rst
Classifier: Development Status :: 4 - Beta
Classifier: Intended Audience :: Developers
Classifier: Intended Audience :: Science/Research
Classifier: Intended Audience :: Manufacturing
Classifier: Operating System :: OS Independent
Classifier: Programming Language :: Python :: 3.10
Classifier: Programming Language :: Python :: 3.11
Classifier: Programming Language :: Python :: 3.12
Classifier: Programming Language :: Python :: 3.13
Classifier: Topic :: Software Development :: Libraries
Classifier: Topic :: Scientific/Engineering :: Electronic Design Automation (EDA)
Classifier: Topic :: Scientific/Engineering :: Information Analysis
Classifier: Operating System :: OS Independent
Requires-Python: <4,>=3.10
License-File: LICENSE
Requires-Dist: grpcio<1.77,>=1.50.0
Requires-Dist: jsonschema
Requires-Dist: psutil
Requires-Dist: pyedb!=0.28.0,>=0.24.0
Requires-Dist: tomli; python_version < "3.11"
Requires-Dist: tomli-w
Requires-Dist: pyyaml
Requires-Dist: defusedxml<8.0,>=0.7
Requires-Dist: numpy<2.3,>=1.20.0
Requires-Dist: pydantic<2.13,>=2.6.4
Provides-Extra: unit-tests
Requires-Dist: pytest<9.1,>=7.4.0; extra == "unit-tests"
Requires-Dist: pytest-cov<7.1,>=4.0.0; extra == "unit-tests"
Requires-Dist: mock<5.3,>=5.1.0; extra == "unit-tests"
Requires-Dist: fpdf2; extra == "unit-tests"
Requires-Dist: requests; extra == "unit-tests"
Requires-Dist: rpyc<6.1,>=6.0.0; extra == "unit-tests"
Requires-Dist: typer>=0.20.0; extra == "unit-tests"
Provides-Extra: integration-tests
Requires-Dist: matplotlib<3.11,>=3.5.0; extra == "integration-tests"
Requires-Dist: pandas<2.4,>=1.1.0; extra == "integration-tests"
Requires-Dist: pyaedt[unit-tests]; extra == "integration-tests"
Provides-Extra: tests
Requires-Dist: ansys-tools-visualization-interface; extra == "tests"
Requires-Dist: openpyxl<3.3,>=3.1.0; extra == "tests"
Requires-Dist: osmnx<2.1,>=1.1.0; extra == "tests"
Requires-Dist: pyaedt[integration-tests]; extra == "tests"
Requires-Dist: pytest-timeout<2.5,>=2.3.0; extra == "tests"
Requires-Dist: pytest-xdist<3.9,>=3.5.0; extra == "tests"
Requires-Dist: pyvista[io]<0.47,>=0.38.0; extra == "tests"
Requires-Dist: scikit-rf<1.10,>=0.30.0; extra == "tests"
Requires-Dist: tables; extra == "tests"
Requires-Dist: cryptography; extra == "tests"
Provides-Extra: dotnet
Requires-Dist: ansys-pythonnet>=3.1.0rc3; extra == "dotnet"
Requires-Dist: cffi<2.1,>=1.16.0; platform_system == "Linux" and extra == "dotnet"
Requires-Dist: dotnetcore2==3.1.23; platform_system == "Linux" and extra == "dotnet"
Requires-Dist: pywin32>=303; platform_system == "Windows" and extra == "dotnet"
Provides-Extra: doc
Requires-Dist: ansys-sphinx-theme<1.7,>=1.0.0; extra == "doc"
Requires-Dist: jupyter; extra == "doc"
Requires-Dist: numpydoc==1.10.0; extra == "doc"
Requires-Dist: recommonmark; extra == "doc"
Requires-Dist: Sphinx<8.3,>=7.1.0; extra == "doc"
Requires-Dist: sphinx-autobuild==2024.10.3; extra == "doc"
Requires-Dist: sphinx-copybutton<0.6,>=0.5.0; extra == "doc"
Requires-Dist: sphinx-gallery<0.21,>=0.14.0; extra == "doc"
Requires-Dist: sphinx_design<0.7,>=0.4.0; extra == "doc"
Requires-Dist: pyvista[io]<0.47,>=0.38.0; extra == "doc"
Requires-Dist: ansys-tools-visualization-interface; extra == "doc"
Requires-Dist: fpdf2; extra == "doc"
Requires-Dist: rpyc<6.1,>=6.0.0; extra == "doc"
Provides-Extra: graphics
Requires-Dist: ansys-tools-visualization-interface; extra == "graphics"
Requires-Dist: pyvista[io]<0.47,>=0.38.0; extra == "graphics"
Requires-Dist: matplotlib<3.11,>=3.5.0; extra == "graphics"
Requires-Dist: vtk<9.6,>=9.0; extra == "graphics"
Requires-Dist: fpdf2; extra == "graphics"
Provides-Extra: jupyter
Requires-Dist: jupyterlab<4.6,>=3.6.0; extra == "jupyter"
Requires-Dist: ipython<9.1,>=7.30.0; extra == "jupyter"
Provides-Extra: all
Requires-Dist: matplotlib<3.11,>=3.5.0; extra == "all"
Requires-Dist: openpyxl<3.3,>=3.1.0; extra == "all"
Requires-Dist: osmnx<2.1,>=1.1.0; extra == "all"
Requires-Dist: pandas<2.4,>=1.1.0; extra == "all"
Requires-Dist: pyvista[io]<0.47,>=0.38.0; extra == "all"
Requires-Dist: fast-simplification>=0.1.7; extra == "all"
Requires-Dist: ansys-tools-visualization-interface; extra == "all"
Requires-Dist: tables; python_version >= "3.10" and extra == "all"
Requires-Dist: scikit-rf<1.10,>=0.30.0; extra == "all"
Requires-Dist: pyaedt[jupyter]; extra == "all"
Requires-Dist: requests; extra == "all"
Requires-Dist: typer>=0.20.0; extra == "all"
Requires-Dist: fpdf2; extra == "all"
Requires-Dist: rpyc<6.1,>=6.0.0; extra == "all"
Requires-Dist: uv>=0.8.17; extra == "all"
Provides-Extra: examples
Requires-Dist: imageio<2.38,>=2.34.0; extra == "examples"
Requires-Dist: matplotlib<3.11,>=3.5.0; extra == "examples"
Requires-Dist: openpyxl<3.3,>=3.1.0; extra == "examples"
Requires-Dist: osmnx<2.1,>=1.1.0; extra == "examples"
Requires-Dist: pandas<2.4,>=1.1.0; extra == "examples"
Requires-Dist: pyvista<0.47,>=0.38.0; extra == "examples"
Requires-Dist: fast-simplification>=0.1.7; extra == "examples"
Requires-Dist: joblib<1.6,>=1.4.0; extra == "examples"
Requires-Dist: plotly<6.6,>=6.0; extra == "examples"
Requires-Dist: scikit-rf<1.10,>=0.30.0; extra == "examples"
Requires-Dist: fpdf2; extra == "examples"
Requires-Dist: rpyc<6.1,>=6.0.0; extra == "examples"
Dynamic: license-file
